human.py
hf_actions/assert/__init__.py
hf_actions/core/__init__.py
hf_actions/math/__init__.py
hf_actions/web/__init__.py
human_framework/VERSION
human_framework/__init__.py
human_framework/action_loader.py
human_framework/templates/report.html
humanframework-0.6.2.dist-info/LICENSE
humanframework-0.6.2.dist-info/METADATA
humanframework-0.6.2.dist-info/WHEEL
humanframework-0.6.2.dist-info/entry_points.txt
humanframework-0.6.2.dist-info/top_level.txt
humanframework-0.6.2.dist-info/RECORD
