Metadata-Version: 2.1
Name: humanframework
Version: 0.6.2
Summary: Human Framework: Test Automation Framework for Humans™
Home-page: https://github.com/roniemartinez/HumanFramework
Author: Ronie Martinez
Author-email: ronmarti18@gmail.com
License: GPLv3
Download-URL: https://github.com/roniemartinez/HumanFramework/tarball/0.6.2
Platform: UNKNOWN
Classifier: Development Status :: 3 - Alpha
Classifier: Natural Language :: English
Classifier: Topic :: Software Development :: Testing
Classifier: License :: OSI Approved :: GNU General Public License v3 (GPLv3)
Classifier: Programming Language :: Python :: 3
Classifier: Programming Language :: Python :: 3.7
Classifier: Programming Language :: Python :: Implementation :: CPython
Requires-Dist: diskcache (==4.0.0)
Requires-Dist: Jinja2 (==2.10.1)
Requires-Dist: python-dotenv (==0.10.3)
Requires-Dist: requests (==2.22.0)
Requires-Dist: selenium (==3.141.0)
